boostbuild/__init__.py
boostbuild/cmd/__init__.py
boostbuild/cmd/delete.py
boostbuild/cmd/print.py
boostbuild/cmd/pwd.py
boostbuild/cmd/unkown.py
boostbuild/context.py
boostbuild/errors.py
boostbuild/main.py
boostbuild/signal_handler.py
boostbuild-0.2.0.dist-info/METADATA
boostbuild-0.2.0.dist-info/entry_points.txt
boostbuild-0.2.0.dist-info/WHEEL
boostbuild-0.2.0.dist-info/LICENSE
boostbuild-0.2.0.dist-info/RECORD
