Metadata-Version: 2.1
Name: boostbuild
Version: 0.2.0
Summary: Boost is a simple build system that aims to create an interface for shell command substitution across different operative systems.
Author: David Lopez
Author-email: davidlopez.hellin@outlook.com
Requires-Python: >=3.7.2,<4.0.0
Classifier: Programming Language :: Python :: 3
Classifier: Programming Language :: Python :: 3.8
Classifier: Programming Language :: Python :: 3.9
Classifier: Programming Language :: Python :: 3.10
Classifier: Programming Language :: Python :: 3.11
Requires-Dist: colorama (>=0.4.6,<0.5.0)
Requires-Dist: pyyaml (>=6.0,<7.0)
